rjgtoys_xc-0.0.3-py3.8-nspkg.pth
rjgtoys/xc/__init__.py
rjgtoys/xc/_json.py
rjgtoys/xc/_raises.py
rjgtoys/xc/_thing.py
rjgtoys/xc/_xc.py
rjgtoys/xc/autodoc.py
rjgtoys/xc/fastapi.py
rjgtoys/xc/raises.py
rjgtoys/xc/starlette.py
rjgtoys_xc-0.0.3.dist-info/LICENSE
rjgtoys_xc-0.0.3.dist-info/METADATA
rjgtoys_xc-0.0.3.dist-info/WHEEL
rjgtoys_xc-0.0.3.dist-info/namespace_packages.txt
rjgtoys_xc-0.0.3.dist-info/top_level.txt
rjgtoys_xc-0.0.3.dist-info/RECORD
