Metadata-Version: 2.1
Name: rjgtoys-xc
Version: 0.0.3
Summary: Structured exceptions for Python
Home-page: https://github.com/bobgautier/rjgtoys-xc
Author: Robert J Gautier
Author-email: bob.gautier@gmail.com
License: UNKNOWN
Platform: UNKNOWN
Classifier: Programming Language :: Python :: 3
Classifier: License :: OSI Approved :: MIT License
Classifier: Operating System :: OS Independent
Requires-Python: >=3.6
Requires-Dist: pydantic
Provides-Extra: autodoc
Requires-Dist: sphinx-autodoc-typehints ; extra == 'autodoc'
Provides-Extra: fastapi
Requires-Dist: fastapi (>=0.61.1) ; extra == 'fastapi'
